{
  "stamp": "2025-08-16T20:23:31.262541Z",
  "input_file": "002_fed_speech.txt",
  "hash_sha256": "d261dd53d88abb35c7da230a7c4c66d9a08df1a6fa6062c03a1f08b33315d3ae",
  "ocers": {
    "O": 1,
    "C": 3,
    "E": 3,
    "R": 1,
    "S": 1,
    "total": 9,
    "verdict": "NEEDS-WORK"
  },
  "notes": {
    "O": "O=1/5 — State observation/uncertainty explicitly; avoid dogma.",
    "C": "C=3/5 — Show premises → inference → conclusion; remove contradictions.",
    "E": "E=3/5 — Add commitments to transparency, clarity, and systemic benefit.",
    "R": "R=1/5 — Include steps or checks another can repeat.",
    "S": "S=1/5 — Add tests/audits and what happens if a check fails."
  }
}